dicaugment/__init__.py
dicaugment/random_utils.py
dicaugment/augmentations/__init__.py
dicaugment/augmentations/functional.py
dicaugment/augmentations/transforms.py
dicaugment/augmentations/utils.py
dicaugment/augmentations/blur/__init__.py
dicaugment/augmentations/blur/functional.py
dicaugment/augmentations/blur/transforms.py
dicaugment/augmentations/crops/__init__.py
dicaugment/augmentations/crops/functional.py
dicaugment/augmentations/crops/transforms.py
dicaugment/augmentations/dicom/__init__.py
dicaugment/augmentations/dicom/functional.py
dicaugment/augmentations/dicom/transforms.py
dicaugment/augmentations/dicom/data/kernels/b10f.npy
dicaugment/augmentations/dicom/data/kernels/b20f.npy
dicaugment/augmentations/dicom/data/kernels/b22f.npy
dicaugment/augmentations/dicom/data/kernels/b26f.npy
dicaugment/augmentations/dicom/data/kernels/b30f.npy
dicaugment/augmentations/dicom/data/kernels/b31f.npy
dicaugment/augmentations/dicom/data/kernels/b35f.npy
dicaugment/augmentations/dicom/data/kernels/b36f.npy
dicaugment/augmentations/dicom/data/kernels/b40f.npy
dicaugment/augmentations/dicom/data/kernels/b41f.npy
dicaugment/augmentations/dicom/data/kernels/b43f.npy
dicaugment/augmentations/dicom/data/kernels/b45f.npy
dicaugment/augmentations/dicom/data/kernels/b46f.npy
dicaugment/augmentations/dicom/data/kernels/b50f.npy
dicaugment/augmentations/dicom/data/kernels/b60f.npy
dicaugment/augmentations/dicom/data/kernels/b70f.npy
dicaugment/augmentations/dicom/data/kernels/b75f.npy
dicaugment/augmentations/dicom/data/kernels/b80f.npy
dicaugment/augmentations/dicom/data/kernels/bone.npy
dicaugment/augmentations/dicom/data/kernels/boneplus.npy
dicaugment/augmentations/dicom/data/kernels/chest.npy
dicaugment/augmentations/dicom/data/kernels/detail.npy
dicaugment/augmentations/dicom/data/kernels/edge.npy
dicaugment/augmentations/dicom/data/kernels/lung.npy
dicaugment/augmentations/dicom/data/kernels/soft.npy
dicaugment/augmentations/dicom/data/kernels/standard.npy
DICaugment-1.0.7.dist-info/LICENSE
DICaugment-1.0.7.dist-info/METADATA
DICaugment-1.0.7.dist-info/WHEEL
DICaugment-1.0.7.dist-info/top_level.txt
DICaugment-1.0.7.dist-info/RECORD
