Metadata-Version: 2.1
Name: DICaugment
Version: 1.0.7
Summary: 3D medical image augmentation library
Home-page: https://github.com/DIDSR/dicaugment
Author: J. McIntosh, M. Mehdi Farhangi
License: MIT
Classifier: Development Status :: 4 - Beta
Classifier: License :: OSI Approved :: MIT License
Classifier: Intended Audience :: Developers
Classifier: Intended Audience :: Science/Research
Classifier: Operating System :: OS Independent
Classifier: Programming Language :: Python
Classifier: Programming Language :: Python :: 3
Classifier: Programming Language :: Python :: 3.8
Classifier: Programming Language :: Python :: 3.9
Classifier: Programming Language :: Python :: 3.10
Classifier: Programming Language :: Python :: 3.11
Classifier: Topic :: Software Development :: Libraries
Classifier: Topic :: Software Development :: Libraries :: Python Modules
Requires-Python: >=3.8
License-File: LICENSE
Requires-Dist: numpy >=1.11.1
Requires-Dist: scipy >=1.10.0
Requires-Dist: scikit-image >=0.16.1
Requires-Dist: PyYAML
Requires-Dist: qudida >=0.0.4
Requires-Dist: pydicom
Requires-Dist: setuptools
Requires-Dist: opencv-python-headless >=4.1.1
Provides-Extra: develop
Requires-Dist: pytest ; extra == 'develop'
Requires-Dist: torch ; extra == 'develop'
Requires-Dist: tensorflow ; extra == 'develop'
Provides-Extra: tensorflow
Requires-Dist: tensorflow ; extra == 'tensorflow'
Provides-Extra: tests
Requires-Dist: pytest ; extra == 'tests'
Provides-Extra: torch
Requires-Dist: torch ; extra == 'torch'
Requires-Dist: torchvision ; extra == 'torch'
Requires-Dist: torchaudio ; extra == 'torch'
